MemPatch/__init__.py
mempatch-0.0.1.dist-info/METADATA
mempatch-0.0.1.dist-info/WHEEL
mempatch-0.0.1.dist-info/top_level.txt
mempatch-0.0.1.dist-info/RECORD
