Metadata-Version: 2.4
Name: mempatch
Version: 0.0.1
Summary: Memory Patch.
Requires-Python: >=3.8
